django_simple_redis/__init__.py
django_simple_redis/redis_connection.py
django_simple_redis-0.0.1.dist-info/DESCRIPTION.rst
django_simple_redis-0.0.1.dist-info/METADATA
django_simple_redis-0.0.1.dist-info/metadata.json
django_simple_redis-0.0.1.dist-info/RECORD
django_simple_redis-0.0.1.dist-info/top_level.txt
django_simple_redis-0.0.1.dist-info/WHEEL
django_simple_redis-0.0.1.dist-info/zip-safe
