Metadata-Version: 2.0
Name: django-simple-redis
Version: 0.0.1
Summary: simplest way to connect to redis on a django application
Home-page: http://github.com/devpopol/django-simple-redis
Author: Stephen Paul Suarez
Author-email: devpopol@gmail.com
License: MIT
Platform: UNKNOWN
Requires-Dist: redis (>=2.9.1)
